scons_remote/__init__.py
scons_remote/action_remote.py
scons_remote/environment_remote.py
scons_remote/utils.py
scons_remote-0.0.1.dist-info/LICENSE
scons_remote-0.0.1.dist-info/METADATA
scons_remote-0.0.1.dist-info/WHEEL
scons_remote-0.0.1.dist-info/top_level.txt
scons_remote-0.0.1.dist-info/RECORD
