Metadata-Version: 2.1
Name: scons-remote
Version: 0.0.1
Summary: Extends SCons to build targets in remote environments.
Home-page: https://github.com/ripl-org/scons-remote
Author: Daniel Molitor
Author-email: connect@ripl.org
Classifier: Development Status :: 3 - Alpha
Classifier: License :: Free for non-commercial use
Classifier: Intended Audience :: Science/Research
Classifier: Natural Language :: English
Classifier: Programming Language :: Python :: 3
Classifier: Topic :: Scientific/Engineering
Requires-Python: >=3.6
License-File: LICENSE
Requires-Dist: boto3
Requires-Dist: fabric
Requires-Dist: scons
